gmailsync/__init__.py
gmailsync/__main__.py
gmailsync/channel.py
gmailsync/cli.py
gmailsync/client.py
gmailsync/mailbox.py
gmailsync/message.py
gmailsync/sync.py
gmailsync/utils.py
gmailsync/config/__init__.py
gmailsync/config/loader.py
gmailsync/config/models.py
gmailsync/config/parser.py
gmailsync/config/validator.py
gmailsync-0.2.0.dist-info/LICENSE
gmailsync-0.2.0.dist-info/METADATA
gmailsync-0.2.0.dist-info/WHEEL
gmailsync-0.2.0.dist-info/entry_points.txt
gmailsync-0.2.0.dist-info/top_level.txt
gmailsync-0.2.0.dist-info/RECORD
